COPYING
INSTALL
MANIFEST.in
NEWS
README
README.sk
pyproject.toml
setup.py
AutoArchive/__init__.py
AutoArchive/_meta.py
AutoArchive/starter.py
AutoArchive/_application/__init__.py
AutoArchive/_application/archiving/__init__.py
AutoArchive/_application/archiving/_archive_info.py
AutoArchive/_application/archiving/_archiving.py
AutoArchive/_application/archiving/_archiving_constants.py
AutoArchive/_application/archiving/_backup_information_provider.py
AutoArchive/_application/archiving/_command_executor.py
AutoArchive/_application/archiving/archiving_application.py
AutoArchive/_application/archiving/_archiver_manipulator/__init__.py
AutoArchive/_application/archiving/_archiver_manipulator/_backup_keeping_manipulations.py
AutoArchive/_application/archiving/_archiver_manipulator/_keeping_id_operations.py
AutoArchive/_application/archiving/_archiver_manipulator/archiver_manipulator.py
AutoArchive/_application/archiving/archive_spec/__init__.py
AutoArchive/_application/archiving/archive_spec/_archive_spec_config_parser.py
AutoArchive/_application/archiving/archive_spec/_sections.py
AutoArchive/_application/archiving/archive_spec/archive_spec.py
AutoArchive/_application/archiving/archive_spec/archive_spec_options.py
AutoArchive/_application/archiving/archive_spec/config_constants.py
AutoArchive/_application/archiving/archive_spec/tests/__init__.py
AutoArchive/_application/archiving/archive_spec/tests/archive_spec_test_utils.py
AutoArchive/_application/archiving/archive_spec/tests/test_archive_spec.py
AutoArchive/_application/archiving/tests/__init__.py
AutoArchive/_application/archiving/tests/archiving_test_utils.py
AutoArchive/_application/archiving/tests/test_archiving/__init__.py
AutoArchive/_application/archiving/tests/test_archiving/configured_archive_info/__init__.py
AutoArchive/_application/archiving/tests/test_archiving/configured_archive_info/test_configured_archive_info.py
AutoArchive/_application/archiving/tests/test_archiving/make_backup/__init__.py
